[
    {
        "fName":"Mahmoud",
        "lName":"Zaki",
        "address":"Alexandria",
        "email":"mahzaki@gmail.com",
        "age":"22",
        "userName":"mah123"
    },
    {
        "fName":"Maryam",
        "lName":"Mohamed",
        "address":"Cairo",
        "email":"marmoh@gmail.com",
        "age":"24",
        "userName":"mar123"
    },
    {
        "fName":"Ahmed",
        "lName":"Mansour",
        "address":"Giza",
        "email":"ahmmans@gmail.com",
        "age":"30",
        "userName":"ahm123"
    },
    {
        "fName":"Radwa",
        "lName":"Darwish",
        "address":"Alexandria",
        "email":"radwa@gmail.com",
        "age":"29",
        "userName":"rad123"
    },
    {
        "fName":"Mai",
        "lName":"Rostom",
        "address":"Mansoura",
        "email":"mairos@gmail.com",
        "age":"26",
        "userName":"mai123"
    }
]